{
  "title": "TextView vertical 15 parameters",
  "type": "TextView",
  "entryPoints": [
    {
      "name": "ATT_BC_RWH2ERROR",
      "connectedData": {
        "formula": "Reporting.ATT_BC_RWH2ERROR<ReportingParameter>.convertedValue",
        "unit": "V",
        "digits": 2,
        "format": "scientific",
        "filter": [{
          "field": "convertedValue",
          "operator": "!=",
          "operand": "0"
        }],
        "domain": "fr.cnes.isis.simupus",
        "timeline": "Session 1"
      }
    },
    {
      "name": "ORB_BC_GPS2NBNANOS",
      "connectedData": {
        "formula": "Reporting.ORB_BC_GPS2NBNANOS<ReportingParameter>.convertedValue",
        "unit": "V",
        "digits": 8,
        "format": "",
        "domain": "fr.cnes.isis.simupus",
        "timeline": "Session 1"
      }
    },
    {
      "name": "ORB_BC_LVPOSZJ2000",
      "connectedData": {
        "formula": "Reporting.ORB_BC_LVPOSZJ2000<ReportingParameter>.convertedValue",
        "unit": "V",
        "digits": 2,
        "format": "scientific",
        "filter": [{
          "field": "convertedValue",
          "operator": "!=",
          "operand": "0"
        }],
        "domain": "fr.cnes.isis.simupus",
        "timeline": "Session 1"
      }
    },
    {
      "name": "ORB_BC_TSTPARVQ",
      "connectedData": {
        "formula": "Reporting.ORB_BC_TSTPARVQ<ReportingParameter>.convertedValue",
        "unit": "V",
        "digits": 8,
        "format": "",
        "domain": "fr.cnes.isis.simupus",
        "timeline": "Session 1"
      }
    },
    {
      "name": "POW_BC_NUMRJCTTC7",
      "connectedData": {
        "formula": "Reporting.POW_BC_NUMRJCTTC7<ReportingParameter>.convertedValue",
        "unit": "V",
        "digits": 2,
        "format": "scientific",
        "filter": [{
          "field": "convertedValue",
          "operator": "!=",
          "operand": "0"
        }],
        "domain": "fr.cnes.isis.simupus",
        "timeline": "Session 1"
      }
    },
    {
      "name": "POW_BC_TSTPARVFLT",
      "connectedData": {
        "formula": "Reporting.POW_BC_TSTPARVFLT<ReportingParameter>.convertedValue",
        "unit": "V",
        "digits": 8,
        "format": "",
        "domain": "fr.cnes.isis.simupus",
        "timeline": "Session 1"
      }
    },
    {
      "name": "SAT_BC_CLOCKFREQ",
      "connectedData": {
        "formula": "Reporting.SAT_BC_CLOCKFREQ<ReportingParameter>.convertedValue",
        "unit": "V",
        "digits": 2,
        "format": "scientific",
        "filter": [{
          "field": "convertedValue",
          "operator": "!=",
          "operand": "0"
        }],
        "domain": "fr.cnes.isis.simupus",
        "timeline": "Session 1"
      }
    },
    {
      "name": "SAT_BC_MNVDEADLRED",
      "connectedData": {
        "formula": "Reporting.SAT_BC_MNVDEADLRED<ReportingParameter>.convertedValue",
        "unit": "V",
        "digits": 8,
        "format": "",
        "domain": "fr.cnes.isis.simupus",
        "timeline": "Session 1"
      }
    },
    {
      "name": "SAT_BC_OFFSETGPS",
      "connectedData": {
        "formula": "Reporting.SAT_BC_OFFSETGPS<ReportingParameter>.convertedValue",
        "unit": "V",
        "digits": 2,
        "format": "scientific",
        "filter": [{
          "field": "convertedValue",
          "operator": "!=",
          "operand": "0"
        }],
        "domain": "fr.cnes.isis.simupus",
        "timeline": "Session 1"
      }
    },
    {
      "name": "SAT_BC_TMFMAXDLT",
      "connectedData": {
        "formula": "Reporting.SAT_BC_TMFMAXDLT<ReportingParameter>.convertedValue",
        "unit": "V",
        "digits": 8,
        "format": "",
        "domain": "fr.cnes.isis.simupus",
        "timeline": "Session 1"
      }
    },
    {
      "name": "MIS_BC_DAGAEN",
      "connectedData": {
        "formula": "Reporting.MIS_BC_DAGAEN<ReportingParameter>.convertedValue",
        "unit": "V",
        "digits": 2,
        "format": "scientific",
        "filter": [{
          "field": "convertedValue",
          "operator": "!=",
          "operand": "0"
        }],
        "domain": "fr.cnes.isis.simupus",
        "timeline": "Session 1"
      }
    },
    {
      "name": "MIS_BC_ENABLED3",
      "connectedData": {
        "formula": "Reporting.MIS_BC_ENABLED3<ReportingParameter>.convertedValue",
        "unit": "V",
        "digits": 8,
        "format": "",
        "domain": "fr.cnes.isis.simupus",
        "timeline": "Session 1"
      }
    },
    {
      "name": "FMGT_BC_NUMRJCTTC14",
      "connectedData": {
        "formula": "Reporting.FMGT_BC_NUMRJCTTC14<ReportingParameter>.convertedValue",
        "unit": "V",
        "digits": 2,
        "format": "scientific",
        "filter": [{
          "field": "convertedValue",
          "operator": "!=",
          "operand": "0"
        }],
        "domain": "fr.cnes.isis.simupus",
        "timeline": "Session 1"
      }
    },
    {
      "name": "FMGT_BC_TCSEQDELAY",
      "connectedData": {
        "formula": "Reporting.FMGT_BC_TCSEQDELAY<ReportingParameter>.convertedValue",
        "unit": "V",
        "digits": 8,
        "format": "",
        "domain": "fr.cnes.isis.simupus",
        "timeline": "Session 1"
      }
    },
    {
      "name": "OBCPE1_BC_NUMRJCTTC0",
      "connectedData": {
        "formula": "Reporting.OBCPE1_BC_NUMRJCTTC0<ReportingParameter>.convertedValue",
        "unit": "V",
        "digits": 2,
        "format": "scientific",
        "filter": [{
          "field": "convertedValue",
          "operator": "!=",
          "operand": "0"
        }],
        "domain": "fr.cnes.isis.simupus",
        "timeline": "Session 1"
      }
    }
  ],
  "links": [
    {
      "name": "pageMedium",
      "path": "../pageMedium.json"
    }
  ],
  "defaultRatio": {
    "length": 5,
    "width": 3
  },
  "content": [
    "<style>",
    "  .myTextView {float: left; font-size: 1.2rem; }",
    "  .myTextView .myContener { background-color: #c5ccd3; margin-top: 8px; margin-left: 12px; padding:0.3em; float: left; border-radius: 5px; border: 2px ridge #596673; height: 80px; width: 200px; }",
    "  .myContener .name {display: block;  border-radius: 5px; overflow: hidden; margin-left: 10px; background-color: white; color: black; font-weight: bolder; margin-top: 5px;text-align: center;}",
    "  .myContener .value { display: block; border-radius: 5px;  overflow: hidden; margin-left: 10px; background-color: black; color: #00ff00; font-weight: bold; text-align: left; padding: 10px; margin-bottom: 10px; }",
    "</style>",
    "<div class='myTextView'>",
    "    <div class='myContener'><span class='name'>ATT_BC_RWH2ERROR</span><span class='value'>{{ATT_BC_RWH2ERROR}}</span></div>",
    "    <div class='myContener'><span class='name'>ORB_BC_GPS2NBNANOS</span><span class='value'>{{ORB_BC_GPS2NBNANOS}}</span></div>",
    "    <div class='myContener'><span class='name'>ORB_BC_LVPOSZJ2000</span><span class='value'>{{ORB_BC_LVPOSZJ2000}}</span></div>",
    "    <div class='myContener'><span class='name'>ORB_BC_TSTPARVQ</span><span class='value'>{{ORB_BC_TSTPARVQ}}</span></div>",
    "    <div class='myContener'><span class='name'>POW_BC_NUMRJCTTC7</span><span class='value'>{{POW_BC_NUMRJCTTC7}}</span></div>",
    "    <div class='myContener'><span class='name'>POW_BC_TSTPARVFLT</span><span class='value'>{{POW_BC_TSTPARVFLT}}</span></div>",
    "    <div class='myContener'><span class='name'>SAT_BC_CLOCKFREQ</span><span class='value'>{{SAT_BC_CLOCKFREQ}}</span></div>",
    "    <div class='myContener'><span class='name'>SAT_BC_MNVDEADLRED</span><span class='value'>{{SAT_BC_MNVDEADLRED}}</span></div>",
    "    <div class='myContener'><span class='name'>SAT_BC_OFFSETGPS</span><span class='value'>{{SAT_BC_OFFSETGPS}}</span></div>",
    "    <div class='myContener'><span class='name'>SAT_BC_TMFMAXDLT</span><span class='value'>{{SAT_BC_TMFMAXDLT}}</span></div>",
    "    <div class='myContener'><span class='name'>MIS_BC_DAGAEN</span><span class='value'>{{MIS_BC_DAGAEN}}</span></div>",
    "    <div class='myContener'><span class='name'>MIS_BC_ENABLED3</span><span class='value'>{{MIS_BC_ENABLED3}}</span></div>",
    "    <div class='myContener'><span class='name'>FMGT_BC_NUMRJCTTC14</span><span class='value'>{{FMGT_BC_NUMRJCTTC14}}</span></div>",
    "    <div class='myContener'><span class='name'>FMGT_BC_TCSEQDELAY</span><span class='value'>{{FMGT_BC_TCSEQDELAY}}</span></div>",
    "    <div class='myContener'><span class='name'>OBCPE1_BC_NUMRJCTTC0</span><span class='value'>{{OBCPE1_BC_NUMRJCTTC0}}</span></div>",
    "</div>"
  ]
}
